filebeat_scrubber/__init__.py
filebeat_scrubber/filebeat_scrubber.py
filebeat_scrubber-1.2.0.dist-info/LICENSE
filebeat_scrubber-1.2.0.dist-info/METADATA
filebeat_scrubber-1.2.0.dist-info/WHEEL
filebeat_scrubber-1.2.0.dist-info/entry_points.txt
filebeat_scrubber-1.2.0.dist-info/top_level.txt
filebeat_scrubber-1.2.0.dist-info/RECORD
