Metadata-Version: 2.1
Name: filebeat-scrubber
Version: 1.2.0
Summary: Filebeat Scrubber performs operations on files that Filebeat has fully harvested.
Home-page: https://github.com/barqshasbite/filebeat-scrubber
Author: barqshasbite
License: UNKNOWN
Platform: UNKNOWN
Classifier: Programming Language :: Python :: 3
Classifier: License :: OSI Approved :: MIT License
Classifier: Operating System :: OS Independent
Requires-Python: >=3.5
